python_notion_to_md/__init__.py
python_notion_to_md/python_notion_to_md.py
python_notion_to_md/utils/__init__.py
python_notion_to_md/utils/exceptions.py
python_notion_to_md/utils/md.py
python_notion_to_md/utils/notion.py
python_notion_to_md/utils/types.py
python_notion_to_md-0.1.6.dist-info/METADATA
python_notion_to_md-0.1.6.dist-info/WHEEL
python_notion_to_md-0.1.6.dist-info/licenses/LICENSE
python_notion_to_md-0.1.6.dist-info/RECORD
