Metadata-Version: 2.4
Name: python_notion_to_md
Version: 0.1.6
Summary: Convert Notion pages to Markdown - Python port of notion-to-md
Author-email: Emre Coklar <emre.coklar@gmail.com>
Maintainer-email: Emre Coklar <emre.coklar@gmail.com>
License: MIT
License-File: LICENSE
Keywords: api-client,converter,markdown,notion
Classifier: Development Status :: 4 - Beta
Classifier: License :: OSI Approved :: MIT License
Classifier: Operating System :: OS Independent
Classifier: Programming Language :: Python :: 3.8
Classifier: Programming Language :: Python :: 3.9
Classifier: Programming Language :: Python :: 3.10
Classifier: Programming Language :: Python :: 3.11
Classifier: Programming Language :: Python :: 3.12
Classifier: Topic :: Software Development :: Libraries
Classifier: Topic :: Text Processing :: Markup :: Markdown
Requires-Python: >=3.8
Requires-Dist: aiohttp>=3.8.0
Requires-Dist: notion-client>=2.0.0
Requires-Dist: tenacity>=8.0.0
